modkit/__init__.py
modkit/classtools/__init__.py
modkit/classtools/_possibility.py
modkit/classtools/_possibility.pyi
modkit/classtools/_property.py
modkit/classtools/_property.pyi
modkit/classtools/exceptions.py
modkit/typing/__init__.py
modkit/typing/_override.py
modkit/typing/_override.pyi
modkit/typing/exceptions.py
modkit-1.3.0.dist-info/LICENSE
modkit-1.3.0.dist-info/METADATA
modkit-1.3.0.dist-info/WHEEL
modkit-1.3.0.dist-info/top_level.txt
modkit-1.3.0.dist-info/RECORD
