Metadata-Version: 2.1
Name: modkit
Version: 1.3.0
Summary: A kit containing tools for better programming.
Author-email: Soumyo Deep Gupta <deep.main.ac@gmail.com>
Maintainer-email: Soumyo Deep Gupta <deep.main.ac@gmail.com>
License: MIT License
Project-URL: GitHub, https://github.com/d33p0st/modkit
Project-URL: Issues, https://github.com/d33p0st/modkit/issues
Project-URL: Pull-Request, https://github.com/d33p0st/modkit/pulls
Keywords: d33p0st,modkit,modstore,module,kit
Requires-Python: >=3.8
License-File: LICENSE
